README.md
setup.cfg
setup.py
beecolpy/__init__.py
beecolpy/beecolpy.py
beecolpy.egg-info/PKG-INFO
beecolpy.egg-info/SOURCES.txt
beecolpy.egg-info/dependency_links.txt
beecolpy.egg-info/requires.txt
beecolpy.egg-info/top_level.txt
beecolpy/tests/__init__.py
beecolpy/tests/test_beecolpy.py