Metadata-Version: 2.1
Name: beecolpy
Version: 2.0
Summary: Artificial Bee Colony solver
Home-page: https://github.com/renard162/BeeColPy
Author: Samuel Carlos Pessoa Oliveira
Author-email: samuelcpoliveira@gmail.com
License: MIT
Keywords: PSO,ABC,Bee,Colony,Binary,Angle Modulated,Solver,Optimize,metaheuristic
Platform: UNKNOWN
Classifier: Development Status :: 5 - Production/Stable
Classifier: Programming Language :: Python :: 3
Classifier: License :: OSI Approved :: MIT License
Classifier: Operating System :: OS Independent
Requires-Python: >=3.0
